tests/__init__.py
tests/conftest.py
tests/test_helpers.py
tests/test_info.py
tests/test_mime.py
tests/test_parser.py
tests/test_pop_server.py
tests/test_server.py
tests/test_smtp_server.py
tests/test_utils.py
zmail/__init__.py
zmail/abc.py
zmail/api.py
zmail/compat.py
zmail/exceptions.py
zmail/helpers.py
zmail/info.py
zmail/mime.py
zmail/parser.py
zmail/server.py
zmail/settings.py
zmail/structures.py
zmail/utils.py
zmail-0.2.8.dist-info/LICENSE
zmail-0.2.8.dist-info/METADATA
zmail-0.2.8.dist-info/WHEEL
zmail-0.2.8.dist-info/top_level.txt
zmail-0.2.8.dist-info/RECORD
