Metadata-Version: 1.1
Name: zmail
Version: 0.2.8
Summary: Zmail makes it easier to send and retrieve emails in python3.
Home-page: https://github.com/ZYunH/zmail
Author: ZYunH
Author-email: zyunhjob@163.com
License: MIT Licence
Keywords: email python3 package
Platform: all
Classifier: Development Status :: 5 - Production/Stable
Classifier: Intended Audience :: Developers
Classifier: License :: OSI Approved :: MIT License
Classifier: Natural Language :: English
Classifier: Operating System :: OS Independent
Classifier: Programming Language :: Python :: 3
Classifier: Programming Language :: Python :: 3.5
Classifier: Programming Language :: Python :: 3.6
Classifier: Programming Language :: Python :: 3.7
Classifier: Programming Language :: Python :: Implementation
Classifier: Programming Language :: Python :: Implementation :: CPython
Classifier: Topic :: Software Development :: Libraries :: Python Modules
